screen3.py
screen3-0.1.2.dist-info/LICENSE
screen3-0.1.2.dist-info/METADATA
screen3-0.1.2.dist-info/WHEEL
screen3-0.1.2.dist-info/top_level.txt
screen3-0.1.2.dist-info/zip-safe
screen3-0.1.2.dist-info/RECORD
