Metadata-Version: 2.1
Name: screen3
Version: 0.1.2
Summary: Thin Python wrapper for the SCREEN3 point source dispersion model
Home-page: https://github.com/zmoon/screen3
Author: Zachary Moon
Author-email: zlm1@psu.edu
License: MIT
Platform: any
Classifier: Programming Language :: Python :: 3
Requires-Python: <4,>=3.6
License-File: LICENSE
Requires-Dist: matplotlib
Requires-Dist: numpy
Requires-Dist: pandas
Requires-Dist: requests
Provides-Extra: docs
Requires-Dist: pdoc; extra == "docs"
